esihub/__init__.py
esihub/api/__init__.py
esihub/api/endpoints.py
esihub/auth.py
esihub/client.py
esihub/core/__init__.py
esihub/core/async_profiler.py
esihub/core/background_tasks.py
esihub/core/cache.py
esihub/core/config.py
esihub/core/connection_pool.py
esihub/core/dry_run.py
esihub/core/error_handler.py
esihub/core/event_system.py
esihub/core/logger.py
esihub/core/metrics.py
esihub/core/rate_limiter.py
esihub/exceptions.py
esihub/models.py
esihub/swagger.json
esihub/utils.py
esihub-0.0.4.dist-info/LICENSE
esihub-0.0.4.dist-info/METADATA
esihub-0.0.4.dist-info/WHEEL
esihub-0.0.4.dist-info/RECORD
