Metadata-Version: 2.1
Name: esihub
Version: 0.0.4
Summary: An asynchronous client library for EVE ONLINE ESI API
Home-page: https://github.com/siege-green/esihub
License: MIT
Keywords: eve online,sdk,api,esi
Author: MelonCafe
Author-email: contact@siege-green.com
Requires-Python: >=3.11,<4.0
Classifier: Development Status :: 3 - Alpha
Classifier: Intended Audience :: Developers
Classifier: License :: OSI Approved :: MIT License
Classifier: Operating System :: OS Independent
Classifier: Programming Language :: Python :: 3
Classifier: Programming Language :: Python :: 3.11
Classifier: Programming Language :: Python :: 3.12
Requires-Dist: aiohttp (>=3.8.0,<4.0.0)
Requires-Dist: black (>=24.3.0,<25.0.0)
Requires-Dist: cachetools (>=5.4.0,<6.0.0)
Requires-Dist: cryptography (>=42.0.8,<43.0.0)
Requires-Dist: fakeredis[aioredis] (>=2.23.3,<3.0.0)
Requires-Dist: flake8 (>=7.1.0,<8.0.0)
Requires-Dist: isort (>=5.10.0,<6.0.0)
Requires-Dist: mkdocs (>=1.6.0,<2.0.0)
Requires-Dist: mkdocs-git-revision-date-localized-plugin (>=1.2.6,<2.0.0)
Requires-Dist: mkdocs-i18n (>=0.4.6,<0.5.0)
Requires-Dist: mkdocs-material (>=9.5.29,<10.0.0)
Requires-Dist: mkdocs-minify-plugin (>=0.8.0,<0.9.0)
Requires-Dist: mypy (>=1.0.0,<2.0.0)
Requires-Dist: prometheus-client (>=0.20.0,<0.21.0)
Requires-Dist: pydantic (>=2.0.0,<3.0.0)
Requires-Dist: pytest (>=7.0.0,<8.0.0)
Requires-Dist: pytest-asyncio (>=0.20.0,<0.21.0)
Requires-Dist: pytest-cov (>=5.0.0,<6.0.0)
Requires-Dist: redis[hiredis] (>=5.0.7,<6.0.0)
Project-URL: Documentation, https://esihub.siege-green.com
Project-URL: Repository, https://github.com/siege-green/esihub
